reachy_mini/__init__.py
reachy_mini/reachy_mini.py
reachy_mini/apps/__init__.py
reachy_mini/apps/app.py
reachy_mini/apps/assistant.py
reachy_mini/apps/manager.py
reachy_mini/apps/utils.py
reachy_mini/apps/sources/__init__.py
reachy_mini/apps/sources/hf_auth.py
reachy_mini/apps/sources/hf_space.py
reachy_mini/apps/sources/local_common_venv.py
reachy_mini/apps/templates/README.md.j2
reachy_mini/apps/templates/gitignore.j2
reachy_mini/apps/templates/index.html.j2
reachy_mini/apps/templates/main.py.j2
reachy_mini/apps/templates/pyproject.toml.j2
reachy_mini/apps/templates/style.css.j2
reachy_mini/apps/templates/static/index.html.j2
reachy_mini/apps/templates/static/main.js.j2
reachy_mini/apps/templates/static/style.css.j2
reachy_mini/assets/confused1.wav
reachy_mini/assets/count.wav
reachy_mini/assets/dance1.wav
reachy_mini/assets/go_sleep.wav
reachy_mini/assets/impatient1.wav
reachy_mini/assets/kinematics_data.json
reachy_mini/assets/wake_up.wav
reachy_mini/assets/config/hardware_config.yaml
reachy_mini/assets/firmware/CHANGELOG.md
reachy_mini/assets/firmware/reachymini_ua_io16_lin_v2.1.2.bin
reachy_mini/assets/firmware/reachymini_ua_io16_lin_v2.1.3.bin
reachy_mini/assets/firmware/update.sh
reachy_mini/assets/models/fknetwork.dynamic.onnx
reachy_mini/assets/models/fknetwork.onnx
reachy_mini/assets/models/fknetwork_int8.onnx
reachy_mini/assets/models/iknetwork.onnx
reachy_mini/daemon/__init__.py
reachy_mini/daemon/daemon.py
reachy_mini/daemon/utils.py
reachy_mini/daemon/app/__init__.py
reachy_mini/daemon/app/bg_job_register.py
reachy_mini/daemon/app/dependencies.py
reachy_mini/daemon/app/main.py
reachy_mini/daemon/app/models.py
reachy_mini/daemon/app/dashboard/static/assets/KO-cartoon-static.svg
reachy_mini/daemon/app/dashboard/static/assets/awake-cartoon-static.svg
reachy_mini/daemon/app/dashboard/static/assets/awake-cartoon.svg
reachy_mini/daemon/app/dashboard/static/assets/go-to-sleep-cartoon.svg
reachy_mini-1.2.13.dist-info/licenses/LICENSE
reachy_mini-1.2.13.dist-info/METADATA
reachy_mini-1.2.13.dist-info/WHEEL
reachy_mini-1.2.13.dist-info/entry_points.txt
reachy_mini-1.2.13.dist-info/top_level.txt
reachy_mini-1.2.13.dist-info/RECORD
