Metadata-Version: 2.4
Name: reachy_mini
Version: 1.2.13
Author-email: Pollen Robotics <contact@pollen-robotics.com>
Requires-Python: >=3.10
License-File: LICENSE
Requires-Dist: numpy>=2.2.5
Requires-Dist: scipy<2.0.0,>=1.15.3
Requires-Dist: reachy_mini_motor_controller>=1.5.3
Requires-Dist: eclipse-zenoh~=1.7.0
Requires-Dist: opencv-python<=5.0
Requires-Dist: cv2_enumerate_cameras>=1.2.1
Requires-Dist: psutil
Requires-Dist: jinja2
Requires-Dist: uvicorn[standard]
Requires-Dist: fastapi
Requires-Dist: pyserial
Requires-Dist: huggingface-hub==1.3.0
Requires-Dist: sounddevice==0.5.1
Requires-Dist: soundfile==0.13.1
Requires-Dist: reachy-mini-rust-kinematics>=1.0.3
Requires-Dist: asgiref
Requires-Dist: aiohttp
Requires-Dist: log-throttling==0.0.3
Requires-Dist: pyusb>=1.2.1
Requires-Dist: libusb_package>=1.0.26.3
Requires-Dist: pip>=25
Requires-Dist: rich
Requires-Dist: questionary
Requires-Dist: websockets<16,>=12
Requires-Dist: toml
Requires-Dist: rustypot>=1.4.2
Requires-Dist: pyyaml>=6.0
Requires-Dist: requests>=2.28.0
Provides-Extra: dev
Requires-Dist: pytest; extra == "dev"
Requires-Dist: pytest-asyncio; extra == "dev"
Requires-Dist: ruff==0.12.0; extra == "dev"
Requires-Dist: onshape-to-robot==1.7.6; extra == "dev"
Requires-Dist: pre-commit; extra == "dev"
Requires-Dist: mypy==1.18.2; extra == "dev"
Requires-Dist: types-requests; extra == "dev"
Requires-Dist: types-toml; extra == "dev"
Provides-Extra: examples
Requires-Dist: pynput; extra == "examples"
Provides-Extra: mujoco
Requires-Dist: mujoco==3.3.0; extra == "mujoco"
Provides-Extra: nn-kinematics
Requires-Dist: onnxruntime==1.22.1; extra == "nn-kinematics"
Provides-Extra: placo-kinematics
Requires-Dist: placo==0.9.14; extra == "placo-kinematics"
Provides-Extra: gstreamer
Requires-Dist: PyGObject<=3.46.0,>=3.42.2; extra == "gstreamer"
Requires-Dist: gst-signalling>=1.1.2; extra == "gstreamer"
Provides-Extra: rerun
Requires-Dist: rerun-sdk>=0.27.2; extra == "rerun"
Requires-Dist: urdf-parser-py==0.0.4; extra == "rerun"
Provides-Extra: wireless-version
Requires-Dist: semver<4,>=3; extra == "wireless-version"
Requires-Dist: nmcli>=1.5; extra == "wireless-version"
Requires-Dist: pollen_BMI088_imu_library; extra == "wireless-version"
Requires-Dist: gpiozero>=2.0.0; extra == "wireless-version"
Requires-Dist: lgpio>=0.2.2.0; extra == "wireless-version"
Dynamic: license-file
